typing_validation/__init__.py
typing_validation/py.typed
typing_validation/validation.py
typing_validation/validation_failure.py
typing_validation_fix-1.2.dist-info/LICENSE
typing_validation_fix-1.2.dist-info/METADATA
typing_validation_fix-1.2.dist-info/WHEEL
typing_validation_fix-1.2.dist-info/top_level.txt
typing_validation_fix-1.2.dist-info/RECORD
