Metadata-Version: 2.1
Name: typing-validation-fix
Version: 1.2
Summary: A simple library for runtime type-checking.
Home-page: https://github.com/aviksaikat/typing-validation
Author: aviksaikat
Author-email: saikickkarma@protonmail.com
Project-URL: Bug Tracker, https://github.com/aviksaikat/typing-validation/issues
Classifier: Development Status :: 4 - Beta
Classifier: Programming Language :: Python :: 3.10
Classifier: Programming Language :: Python :: 3.9
Classifier: Programming Language :: Python :: 3.8
Classifier: Programming Language :: Python :: 3.7
Classifier: Operating System :: OS Independent
Classifier: Natural Language :: English
Classifier: Typing :: Typed
Requires-Python: >=3.7
License-File: LICENSE
Requires-Dist: typing-extensions ; python_version < "3.8"
Provides-Extra: dev
Requires-Dist: mypy ; extra == 'dev'
Requires-Dist: pylint ; extra == 'dev'
Requires-Dist: pytest ; extra == 'dev'
Requires-Dist: pytest-cov ; extra == 'dev'
Requires-Dist: rich ; extra == 'dev'
